jismesh/__init__.py
jismesh/utils/__init__.py
jismesh/utils/_scalar.py
jismesh/utils/_vector.py
jismesh-2.1.0.dist-info/LICENSE
jismesh-2.1.0.dist-info/METADATA
jismesh-2.1.0.dist-info/WHEEL
jismesh-2.1.0.dist-info/top_level.txt
jismesh-2.1.0.dist-info/RECORD
