Metadata-Version: 2.1
Name: jismesh
Version: 2.1.0
Summary: Utilities for the Japanese regional grid system defined in Japanese Industrial Standards (JIS X 0410 地域メッシュ).
Home-page: https://github.com/hni14/jismesh
Author: Haruki Nishikawa
Author-email: harukinishikawa84@hotmail.com
License: MIT
Download-URL: https://github.com/hni14/jismesh/archive/v2.1.0.tar.gz
Keywords: mesh,grid,meshcode,mesh code,JIS X 0410
Platform: any
Classifier: Development Status :: 4 - Beta
Classifier: Intended Audience :: Developers
Classifier: License :: OSI Approved :: MIT License
Classifier: Programming Language :: Python :: 2
Classifier: Programming Language :: Python :: 2.7
Classifier: Programming Language :: Python :: 3
Classifier: Programming Language :: Python :: 3.2
Classifier: Programming Language :: Python :: 3.3
Classifier: Programming Language :: Python :: 3.4
Classifier: Programming Language :: Python :: 3.5
Classifier: Programming Language :: Python :: 3.6
Classifier: Programming Language :: Python :: 3.7
Classifier: Programming Language :: Python :: 3.8
Classifier: Programming Language :: Python :: 3.9
Requires-Dist: numpy (>=1.15)
Requires-Dist: functools32 ; python_version < "3.0"
Provides-Extra: test
Requires-Dist: nose (>=1.3.7) ; extra == 'test'
